dataset_parser/__init__.py
dataset_parser/parse_argoverse.py
dataset_parser/parse_dlp.py
dataset_parser/parse_interaction.py
dataset_parser/parse_levelx.py
dataset_parser/parse_ngsim.py
dataset_parser/parse_nuplan.py
dataset_parser/parse_womd.py
dataset_parser/womd_proto/__init__.py
dataset_parser/womd_proto/compressed_lidar_pb2.py
dataset_parser/womd_proto/dataset_pb2.py
dataset_parser/womd_proto/keypoint_pb2.py
dataset_parser/womd_proto/label_pb2.py
dataset_parser/womd_proto/map_pb2.py
dataset_parser/womd_proto/scenario_pb2.py
dataset_parser/womd_proto/vector_pb2.py
envs/__init__.py
envs/parking.py
envs/racing.py
envs/urban.py
map/__init__.py
map/converter/__init__.py
map/converter/gpkg2osm.py
map/converter/xodr2osm.py
map/element/__init__.py
map/element/area.py
map/element/defaults.py
map/element/lane.py
map/element/map.py
map/element/node.py
map/element/regulatory.py
map/element/roadline.py
map/generator/__init__.py
map/generator/generate_parking_lot.py
map/generator/generate_racing_track.py
map/parser/__init__.py
map/parser/fix_osm.py
map/parser/parse_osm.py
map/parser/parse_xodr.py
math/__init__.py
math/random.py
math/geometry/__init__.py
math/geometry/circle.py
math/geometry/vector.py
math/interpolate/__init__.py
math/interpolate/b_spline.py
math/interpolate/bezier.py
math/interpolate/cubic_spline.py
math/interpolate/dubins.py
math/interpolate/reeds_shepp.py
participant/__init__.py
participant/guess_type.py
participant/element/__init__.py
participant/element/cyclist.py
participant/element/defaults.py
participant/element/other.py
participant/element/participant_base.py
participant/element/pedestrian.py
participant/element/vehicle.py
physics/__init__.py
physics/physics_model_base.py
physics/point_mass.py
physics/single_track_dynamics.py
physics/single_track_kinematics.py
sensor/__init__.py
sensor/camera.py
sensor/defaults.py
sensor/lidar.py
sensor/render_manager.py
sensor/sensor_base.py
traffic/__init__.py
traffic/scenario_display.py
tactic-0.0.1.dist-info/LICENSE
tactic-0.0.1.dist-info/METADATA
tactic-0.0.1.dist-info/WHEEL
tactic-0.0.1.dist-info/top_level.txt
tactic-0.0.1.dist-info/RECORD
