Metadata-Version: 2.1
Name: tactic
Version: 0.0.1
Summary: Occpupy this library name for future development of 3D simulator related to tactics2d.
Home-page: https://github.com/WoodOxen/tactics
Author: WoodOxen
Author-email: rowena.academic@gmail.com
Keywords: simulator,autonomous driving
Classifier: Programming Language :: Python :: 3
Classifier: License :: OSI Approved :: GNU Affero General Public License v3
Classifier: Operating System :: POSIX :: Linux
Requires-Python: >=3.7.0
License-File: LICENSE
Requires-Dist: fastparquet >=0.8.1
Requires-Dist: geopandas >=0.10.2
Requires-Dist: gymnasium >=0.28.0
Requires-Dist: joblib >=1.3.2
Requires-Dist: numpy >=1.21.5
Requires-Dist: pandas >=1.3.5
Requires-Dist: protobuf <=3.20.3
Requires-Dist: pygame >=2.5.2
Requires-Dist: pyproj >=3.2.1
Requires-Dist: scikit-learn >=1.0.0
Requires-Dist: tensorflow ==2.11.0
Requires-Dist: shapely ==2.0.2
